dremio_simple_query/__init__.py
dremio_simple_query/config.py
dremio_simple_query/connect.py
dremio_simple_query/connectv2.py
dremio_simple_query-2.0.0.dist-info/licenses/LICENSE
dremio_simple_query-2.0.0.dist-info/METADATA
dremio_simple_query-2.0.0.dist-info/WHEEL
dremio_simple_query-2.0.0.dist-info/top_level.txt
dremio_simple_query-2.0.0.dist-info/RECORD
