Metadata-Version: 2.4
Name: dremio_simple_query
Version: 2.0.0
Summary: Simple tool to query Dremio with Apache Arrow Flight
Author-email: Alex Merced <alex.merced@dremio.com>
Project-URL: Homepage, https://github.com/developer-advocacy-dremio/dremio_simple_query
Project-URL: Bug Tracker, https://github.com/developer-advocacy-dremio/dremio_simple_query/issues
Classifier: Programming Language :: Python :: 3
Classifier: License :: OSI Approved :: MIT License
Classifier: Operating System :: OS Independent
Requires-Python: >=3.7
License-File: LICENSE
Requires-Dist: duckdb>=1.4.3
Requires-Dist: pyarrow>=22.0.0
Requires-Dist: requests>=2.32.5
Requires-Dist: polars>=1.36.1
Requires-Dist: pandas>=2.3.3
Requires-Dist: pyyaml>=6.0
Dynamic: license-file
